{
  "version": 2,
  "query": "software development",
  "location": "20011",
  "paginationPayload": "",
  "radius": 25,
  "dupefilter": true,
  "highlight": true,
  "totalResults": 18358,
  "start": 1,
  "end": 25,
  "pageNumber": 0,
  "results": [
    {
      "jobtitle": "Software Engineering - University graduates",
      "company": "VeriSign",
      "city": "Reston",
      "state": "VA",
      "country": "US",
      "language": "en",
      "formattedLocation": "Reston, VA",
      "source": "VeriSign",
      "date": "Thu, 06 Apr 2017 23:01:40 GMT",
      "snippet": "Have the opportunity to be involved in all phases of <b>software</b> <b>development</b>, including requirements analysis, design, <b>development</b>, automated test, and automated...",
      "url": "http://www.indeed.com/viewjob?jk=66d032cd079cc5ab&qd=7p8d_wl6uIZppOdlI3iNtvmlwm8yq8tJPCMtlhD32kOSCp82l-bMIQMxmuSvnkoKnrUjY4Th4KdVfErIu5FiYLe3Rdf2HzAxwoIDm1sN3FqZn0ax1-T61fZlnEiw8Hbw&indpubnum=8417063092021675&atk=1bduik5tha0mkerm",
      "onmousedown": "indeed_clk(this,'2288');",
      "latitude": 38.956764,
      "longitude": -77.361435,
      "jobkey": "66d032cd079cc5ab",
      "sponsored": false,
      "expired": false,
      "indeedApply": false,
      "formattedLocationFull": "Reston, VA 20190",
      "formattedRelativeTime": "10 days ago",
      "stations": ""
    },
    {
      "jobtitle": "Research Assistant",
      "company": "Center for Global Development",
      "city": "Washington",
      "state": "DC",
      "country": "US",
      "language": "en",
      "formattedLocation": "Washington, DC",
      "source": "Center for Global Development",
      "date": "Mon, 06 Mar 2017 21:40:22 GMT",
      "snippet": "Required <b>software</b> skills:. Conduct statistical analyses and econometric modeling using Stata, Excel, and other <b>software</b> tools, and prepare tables and graphs to...",
      "url": "http://www.indeed.com/viewjob?jk=3b508b648c3e2f7e&qd=7p8d_wl6uIZppOdlI3iNtvmlwm8yq8tJPCMtlhD32kOSCp82l-bMIQMxmuSvnkoKnrUjY4Th4KdVfErIu5FiYLe3Rdf2HzAxwoIDm1sN3FqZn0ax1-T61fZlnEiw8Hbw&indpubnum=8417063092021675&atk=1bduik5tha0mkerm",
      "onmousedown": "indeed_clk(this,'2288');",
      "latitude": 38.892857,
      "longitude": -77.03297,
      "jobkey": "3b508b648c3e2f7e",
      "sponsored": false,
      "expired": false,
      "indeedApply": true,
      "formattedLocationFull": "Washington, DC",
      "formattedRelativeTime": "30+ days ago",
      "stations": ""
    },
    {
      "jobtitle": "Full Stack Developer",
      "company": "Ori.ai",
      "city": "Washington",
      "state": "DC",
      "country": "US",
      "language": "en",
      "formattedLocation": "Washington, DC",
      "source": "Indeed",
      "date": "Tue, 11 Apr 2017 19:29:25 GMT",
      "snippet": "5+ years of experience of application <b>development</b>. Experience with electronic medical record (EMR) and practice management <b>software</b> (PMS) integration is a plus....",
      "url": "http://www.indeed.com/viewjob?jk=1613c54ecc713ead&qd=7p8d_wl6uIZppOdlI3iNtvmlwm8yq8tJPCMtlhD32kOSCp82l-bMIQMxmuSvnkoKnrUjY4Th4KdVfErIu5FiYLe3Rdf2HzAxwoIDm1sN3FqZn0ax1-T61fZlnEiw8Hbw&indpubnum=8417063092021675&atk=1bduik5tha0mkerm",
      "onmousedown": "indeed_clk(this,'2288');",
      "latitude": 38.917583,
      "longitude": -77.03297,
      "jobkey": "1613c54ecc713ead",
      "sponsored": false,
      "expired": false,
      "indeedApply": true,
      "formattedLocationFull": "Washington, DC 20009",
      "formattedRelativeTime": "5 days ago",
      "stations": ""
    },
    {
      "jobtitle": "Software Development Internship",
      "company": "Teaching Strategies, LLC",
      "city": "Bethesda",
      "state": "MD",
      "country": "US",
      "language": "en",
      "formattedLocation": "Bethesda, MD",
      "source": "Indeed",
      "date": "Tue, 11 Apr 2017 15:33:54 GMT",
      "snippet": "Teaching Strategies is looking for highly talented, innovative and creative up and coming <b>software</b> engineers to join our technology <b>development</b> team for the...",
      "url": "http://www.indeed.com/viewjob?jk=8033569133569f30&qd=7p8d_wl6uIZppOdlI3iNtvmlwm8yq8tJPCMtlhD32kOSCp82l-bMIQMxmuSvnkoKnrUjY4Th4KdVfErIu5FiYLe3Rdf2HzAxwoIDm1sN3FqZn0ax1-T61fZlnEiw8Hbw&indpubnum=8417063092021675&atk=1bduik5tha0mkerm",
      "onmousedown": "indeed_clk(this,'2288');",
      "latitude": 38.98045,
      "longitude": -77.09175,
      "jobkey": "8033569133569f30",
      "sponsored": false,
      "expired": false,
      "indeedApply": true,
      "formattedLocationFull": "Bethesda, MD 20814",
      "formattedRelativeTime": "6 days ago",
      "stations": ""
    },
    {
      "jobtitle": "Entry Level Software Developer",
      "company": "NDDSystem llc",
      "city": "Washington",
      "state": "DC",
      "country": "US",
      "language": "en",
      "formattedLocation": "Washington, DC",
      "source": "NDDSystem llc",
      "date": "Sat, 08 Apr 2017 05:20:23 GMT",
      "snippet": "Design and <b>development</b> of <b>software</b> modules from clearly defined functional requirements. Applies a systematic, disciplined, quantifiable approach for the...",
      "url": "http://www.indeed.com/viewjob?jk=1481782936f5c87f&qd=7p8d_wl6uIZppOdlI3iNtvmlwm8yq8tJPCMtlhD32kOSCp82l-bMIQMxmuSvnkoKnrUjY4Th4KdVfErIu5FiYLe3Rdf2HzAxwoIDm1sN3FqZn0ax1-T61fZlnEiw8Hbw&indpubnum=8417063092021675&atk=1bduik5tha0mkerm",
      "onmousedown": "indeed_clk(this,'2288');",
      "latitude": 38.892857,
      "longitude": -77.03297,
      "jobkey": "1481782936f5c87f",
      "sponsored": false,
      "expired": false,
      "indeedApply": false,
      "formattedLocationFull": "Washington, DC",
      "formattedRelativeTime": "9 days ago",
      "stations": ""
    }
  ]
}
